redis_client/__init__.py
redis_client/client.py
redis_client/custom_types.py
redis_client/logger.py
redis_client-1.0.0.dist-info/WHEEL
redis_client-1.0.0.dist-info/METADATA
redis_client-1.0.0.dist-info/RECORD
