Metadata-Version: 2.1
Name: redis-client
Version: 1.0.0
Summary: A simple client for Redis
Home-page: https://github.com/GraphtyLove/redis_client_python
License: MIT
Author: GraphtyLove
Author-email: maxim.berge@gmail.com
Requires-Python: >=3.10,<4.0
Classifier: Intended Audience :: Developers
Classifier: License :: OSI Approved :: MIT License
Classifier: Operating System :: OS Independent
Classifier: Programming Language :: Python
Classifier: Programming Language :: Python :: 3
Classifier: Programming Language :: Python :: 3.10
Classifier: Programming Language :: Python :: 3
Classifier: Programming Language :: Python :: 3 :: Only
Classifier: Programming Language :: Python :: 3.10
Classifier: Typing :: Typed
Requires-Dist: redis (==4.3.4)
Project-URL: Repository, https://github.com/GraphtyLove/redis_client_python
